{
  "db_name": "PostgreSQL",
  "query": "SELECT sequence_num, chain_hash FROM audit_log\n         WHERE server_id = $1\n         ORDER BY sequence_num DESC NULLS LAST, created_at DESC\n         LIMIT 1\n         FOR UPDATE",
  "describe": {
    "columns": [
      {
        "ordinal": 0,
        "name": "sequence_num",
        "type_info": "Int8"
      },
      {
        "ordinal": 1,
        "name": "chain_hash",
        "type_info": "Text"
      }
    ],
    "parameters": {
      "Left": [
        "Uuid"
      ]
    },
    "nullable": [
      true,
      true
    ]
  },
  "hash": "42bfd09f688cc008e111f40ef807789d49a7da9dcadb3a21f233e500a7f24049"
}
